scrolls/__init__.py
scrolls/run.py
scrolls/version.py
scrolls/chat/famous-person.txt
scrolls/chat/internal-monologue.txt
scrolls/chat/sam-and-max.txt
scrolls/chat/sassy-chat.txt
scrolls/comedy/knock-knock.txt
scrolls/comedy/snarky-movie-summary.txt
scrolls/creative/business-ideas.txt
scrolls/creative/cooking-recipes-from-ingredients.txt
scrolls/creative/philosopher.json
scrolls/creative/philosopher.txt
scrolls/creative/self-aware.txt
scrolls/games/dog.txt
scrolls/games/text-adventure.txt
scrolls/introspection/q-and-a-steps.txt
scrolls/productivity/email-writing.txt
scrolls/rephrase/acronyms.txt
scrolls/rephrase/analogies.txt
scrolls/rephrase/complicate-it.txt
scrolls/rephrase/conceptual-blending.txt
scrolls/rephrase/email-expand.txt
scrolls/rephrase/email-soften.txt
scrolls/rephrase/how-to.txt
scrolls/rephrase/shorten.txt
scrolls/rephrase/simplify.txt
scrolls/rephrase/text-to-emoji.txt
scrolls/rephrase/tonedown.txt
scrolls/self/gpt-3-website.txt
scrolls/self/gpt3-blog.txt
scrolls/self/openai-ideas.txt
scrolls/spanish/borges-poems.txt
scrolls/spanish/borges-story.txt
scrolls/spanish/drexler-lyrics.txt
scrolls/spanish/onu-taskforce.txt
scrolls/top10/men.txt
scrolls/top10/women.json
scrolls/top10/women.txt
scrolls/tweets/twitter-fiction.txt
gpt_scrolls-0.0.9.dist-info/LICENSE
gpt_scrolls-0.0.9.dist-info/METADATA
gpt_scrolls-0.0.9.dist-info/WHEEL
gpt_scrolls-0.0.9.dist-info/top_level.txt
gpt_scrolls-0.0.9.dist-info/RECORD
