Metadata-Version: 2.1
Name: gpt-scrolls
Version: 0.0.9
Summary: A collaborative collection of open-source safe GPT-3 prompts that work well
Home-page: https://github.com/maraoz/gpt-scrolls
Author: Manuel Araoz
Author-email: gpt-scrolls@maraoz.com
License: UNKNOWN
Platform: UNKNOWN
Classifier: Programming Language :: Python :: 3
Classifier: License :: OSI Approved :: MIT License
Classifier: Operating System :: OS Independent
Requires-Python: >=3.6
Requires-Dist: openai (<1.0.0,>=0.2.4)
